aioloop_proxy/__init__.py
aioloop_proxy/_api.py
aioloop_proxy/_handle.py
aioloop_proxy/_loop.py
aioloop_proxy/_protocol.py
aioloop_proxy/_server.py
aioloop_proxy/_task.py
aioloop_proxy/_transport.py
aioloop_proxy/_version.py
aioloop_proxy/py.typed
aioloop_proxy-0.0.13.dist-info/METADATA
aioloop_proxy-0.0.13.dist-info/WHEEL
aioloop_proxy-0.0.13.dist-info/top_level.txt
aioloop_proxy-0.0.13.dist-info/RECORD
