Metadata-Version: 2.1
Name: aioloop-proxy
Version: 0.0.13
Summary: Asyncio loop proxy for testing purposes
Home-page: https://github.com/aio-libs/aiohttp
Maintainer: aiohttp team <team@aiohttp.org>
Maintainer-email: team@aiohttp.org
License: Apache 2
Project-URL: Chat: Gitter, https://gitter.im/aio-libs/Lobby
Project-URL: CI: GitHub Actions, https://github.com/aio-libs/aioloop-proxy/actions?query=workflow%3ACI
Project-URL: Coverage: codecov, https://codecov.io/github/aio-libs/aioloop-proxy
Project-URL: GitHub: issues, https://github.com/aio-libs/aioloop-proxy/issues
Project-URL: GitHub: repo, https://github.com/aio-libs/aioloop-proxy
Platform: UNKNOWN
Classifier: Development Status :: 4 - Beta
Classifier: Framework :: AsyncIO
Classifier: Intended Audience :: Developers
Classifier: Topic :: Software Development :: Testing
Classifier: License :: OSI Approved :: Apache Software License
Classifier: Operating System :: POSIX
Classifier: Operating System :: MacOS :: MacOS X
Classifier: Operating System :: Microsoft :: Windows
Classifier: Programming Language :: Python
Classifier: Programming Language :: Python :: 3
Classifier: Programming Language :: Python :: 3.7
Classifier: Programming Language :: Python :: 3.8
Classifier: Programming Language :: Python :: 3.9
Classifier: Programming Language :: Python :: 3.10
Classifier: Typing :: Typed
Requires-Python: >=3.7.0
Requires-Dist: typing-extensions (>=4.0) ; python_version < "3.8"
